LICENSE
MANIFEST.in
README.rst
setup.cfg
setup.py
chatovod/__init__.py
chatovod/test_cases.py
chatovod/test_settings.py
chatovod/test_urls.py
chatovod/templates/chatovod/chat.html
chatovod/templatetags/__init__.py
chatovod/templatetags/chatovod.py
chatovod/templatetags/defaults.py
django_chatovod.egg-info/PKG-INFO
django_chatovod.egg-info/SOURCES.txt
django_chatovod.egg-info/dependency_links.txt
django_chatovod.egg-info/not-zip-safe
django_chatovod.egg-info/top_level.txt
docs/__init__.py
docs/conf.py